[{"estacion": "Aranguren, Ilundain", "codigo": "9263X", "coordenadas": "42\u00b0 46' 34'' N | 1\u00b0 31' 57'' O", "seguimiento": null, "prealerta": null, "alerta": null}, {"estacion": "Areso", "codigo": "1033X", "coordenadas": "43\u00b0 5' 6'' N | 1\u00b0 57' 3'' O", "seguimiento": null, "prealerta": null, "alerta": null}, {"estacion": "Bardenas Reales, Base A\u00e9rea", "codigo": "9294E", "coordenadas": "42\u00b0 11' 55'' N | 1\u00b0 28' 31'' O", "seguimiento": null, "prealerta": null, "alerta": null}, {"estacion": "Baztan, Irurita", "codigo": "1002Y", "coordenadas": "43\u00b0 8' 9'' N | 1\u00b0 32' 35'' O", "seguimiento": null, "prealerta": null, "alerta": null}, {"estacion": "Bera", "codigo": "1010X", "coordenadas": "43\u00b0 16' 43'' N | 1\u00b0 40' 33'' O", "seguimiento": null, "prealerta": null, "alerta": null}, {"estacion": "C\u00e1seda", "codigo": "9245X", "coordenadas": "42\u00b0 31' 17'' N | 1\u00b0 21' 59'' O", "seguimiento": null, "prealerta": null, "alerta": null}, {"estacion": "Esteribar, Embalse de Eugi", "codigo": "9257X", "coordenadas": "42\u00b0 58' 14'' N | 1\u00b0 31' 1'' O", "seguimiento": null, "prealerta": null, "alerta": null}, {"estacion": "Irurtzun", "codigo": "9274X", "coordenadas": "42\u00b0 55' 8'' N | 1\u00b0 50' 6'' O", "seguimiento": null, "prealerta": null, "alerta": null}, {"estacion": "Isaba/Izaba", "codigo": "9218A", "coordenadas": "42\u00b0 51' 44'' N | 0\u00b0 55' 29'' O", "seguimiento": null, "prealerta": null, "alerta": null}, {"estacion": "Larraga", "codigo": "9280B", "coordenadas": "42\u00b0 32' 58'' N | 1\u00b0 51' 27'' O", "seguimiento": null, "prealerta": null, "alerta": null}, {"estacion": "Los Arcos", "codigo": "9171K", "coordenadas": "42\u00b0 34' 13'' N | 2\u00b0 11' 2'' O", "seguimiento": null, "prealerta": null, "alerta": null}, {"estacion": "Monreal/Elo", "codigo": "9262P", "coordenadas": "42\u00b0 42' 4'' N | 1\u00b0 29' 44'' O", "seguimiento": null, "prealerta": null, "alerta": null}, {"estacion": "Monteagudo", "codigo": "9301X", "coordenadas": "41\u00b0 57' 32'' N | 1\u00b0 41' 26'' O", "seguimiento": null, "prealerta": null, "alerta": null}, {"estacion": "Navascu\u00e9s/Nabaskoze", "codigo": "9238X", "coordenadas": "42\u00b0 43' 2'' N | 1\u00b0 7' 1'' O", "seguimiento": null, "prealerta": null, "alerta": null}, {"estacion": "Olite/Erriberri", "codigo": "9252X", "coordenadas": "42\u00b0 29' 21'' N | 1\u00b0 39' 20'' O", "seguimiento": null, "prealerta": null, "alerta": null}, {"estacion": "Oroz-Betelu/Orotz-Betelu", "codigo": "9228J", "coordenadas": "42\u00b0 53' 46'' N | 1\u00b0 18' 1'' O", "seguimiento": null, "prealerta": null, "alerta": null}, {"estacion": "Pamplona, Aeropuerto", "codigo": "9263D", "coordenadas": "42\u00b0 46' 37'' N | 1\u00b0 39' 0'' O", "seguimiento": null, "prealerta": null, "alerta": null}, {"estacion": "Roncesvalles/Orreaga", "codigo": "9228T", "coordenadas": "43\u00b0 0' 28'' N | 1\u00b0 19' 32'' O", "seguimiento": null, "prealerta": null, "alerta": null}, {"estacion": "Tudela", "codigo": "9302Y", "coordenadas": "42\u00b0 3' 20'' N | 1\u00b0 36' 34'' O", "seguimiento": null, "prealerta": null, "alerta": null}, {"estacion": "Valcarlos/Luzaide", "codigo": "9995Y", "coordenadas": "43\u00b0 5' 28'' N | 1\u00b0 18' 3'' O", "seguimiento": null, "prealerta": null, "alerta": null}]